<?xml version="1.0" encoding="UTF-8"?>
<oslc4j_ai:Specification xmi:version="2.0" xmlns:xmi="http://www.omg.org/XMI" xmlns:xsi="http://www.w3.org/2001/XMLSchema-instance" xmlns:oslc4j_ai="http://org.eclipse.lyo/oslc4j/adaptorInterface">
  <domainSpecifications name="Dublin Core" namespaceURI="http://purl.org/dc/terms/" namespacePrefix="//@domainPrefixes[name='dcterms']">
    <resourceProperties id="_pna4kZUdEeq-KoPaR9_Cfg" name="contributor" description="Contributor or contributors to the resource. It is likely that the target resource will be a foaf:Person but that is not necessarily the case." occurs="zeroOrMany" valueType="Resource" range="_posq8JUdEeq-KoPaR9_Cfg" representation="either">
      <propertyDefinition href="vocabulary.xml#//@vocabularies[label='Dublin%20Core']/@properties[name='contributor']"/>
    </resourceProperties>
    <resourceProperties id="_pna4kJUdEeq-KoPaR9_Cfg" name="creator" description="Creator or creators of the resource. It is likely that the target resource will be a foaf:Person but that is not necessarily the case." occurs="zeroOrMany" valueType="Resource" range="_posq8JUdEeq-KoPaR9_Cfg" representation="either">
      <propertyDefinition href="vocabulary.xml#//@vocabularies[label='Dublin%20Core']/@properties[name='creator']"/>
    </resourceProperties>
    <resourceProperties id="_pnXOMZUdEeq-KoPaR9_Cfg" name="created" description="Timestamp of resource creation" occurs="zeroOrOne" valueType="DateTime">
      <propertyDefinition href="vocabulary.xml#//@vocabularies[label='Dublin%20Core']/@properties[name='created']"/>
    </resourceProperties>
    <resourceProperties id="_pnXOMpUdEeq-KoPaR9_Cfg" name="description" description="Descriptive text about resource represented as rich text in XHTML content. SHOULD include only content that is valid and suitable inside an XHTML &lt;div> element." occurs="zeroOrOne" valueType="XMLLiteral">
      <propertyDefinition href="vocabulary.xml#//@vocabularies[label='Dublin%20Core']/@properties[name='description']"/>
    </resourceProperties>
    <resourceProperties id="_pnX1QJUdEeq-KoPaR9_Cfg" name="identifier" description="A unique identifier for a resource. Typically read-only and assigned by the service provider when a resource is created. Not typically intended for end-user display." valueType="String">
      <propertyDefinition href="vocabulary.xml#//@vocabularies[label='Dublin%20Core']/@properties[name='identifier']"/>
    </resourceProperties>
    <resourceProperties id="_pnYcUJUdEeq-KoPaR9_Cfg" name="modified" description="Timestamp of latest resource modification" occurs="zeroOrOne" valueType="DateTime">
      <propertyDefinition href="vocabulary.xml#//@vocabularies[label='Dublin%20Core']/@properties[name='modified']"/>
    </resourceProperties>
    <resourceProperties id="_pozYoJUdEeq-KoPaR9_Cfg" name="relation" description="Relation which identifies a related resource." valueType="Resource">
      <propertyDefinition href="vocabulary.xml#//@vocabularies[label='Dublin%20Core']/@properties[name='relation']"/>
    </resourceProperties>
    <resourceProperties id="_pnYcUZUdEeq-KoPaR9_Cfg" title="" name="subject" description="Tag or keyword for a resource. Each occurrence of a dcterms:subject property denotes an additional tag for the resource." occurs="zeroOrMany" valueType="String">
      <propertyDefinition href="vocabulary.xml#//@vocabularies[label='Dublin%20Core']/@properties[name='subject']"/>
    </resourceProperties>
    <resourceProperties id="_pnZDYJUdEeq-KoPaR9_Cfg" name="title" description="Title of the resource represented as rich text in XHTML content. SHOULD include only content that is valid inside an XHTML &lt;span> element." valueType="XMLLiteral">
      <propertyDefinition href="vocabulary.xml#//@vocabularies[label='Dublin%20Core']/@properties[name='title']"/>
    </resourceProperties>
    <resourceProperties id="_pnX1QZUdEeq-KoPaR9_Cfg" name="isVersionOf" description="The concept resource of which this resource is a version. The subject of this property must be the version resource URI." valueType="Resource" representation="reference">
      <propertyDefinition href="vocabulary.xml#//@vocabularies[label='Dublin%20Core']/@properties[name='isVersionOf']"/>
    </resourceProperties>
    <resourceProperties id="_pozYoZUdEeq-KoPaR9_Cfg" name="hasPart" description="A related resource that is included either physically or logically in the described resource." occurs="zeroOrMany" valueType="Resource">
      <propertyDefinition href="vocabulary.xml#//@vocabularies[label='Dublin%20Core']/@properties[name='hasPart']"/>
    </resourceProperties>
    <resourceProperties id="_poqOsJUdEeq-KoPaR9_Cfg" name="source" occurs="zeroOrOne" valueType="URI">
      <propertyDefinition href="vocabulary.xml#//@vocabularies[label='Dublin%20Core']/@properties[name='source']"/>
    </resourceProperties>
    <resourceProperties id="_poqOsZUdEeq-KoPaR9_Cfg" name="type" occurs="zeroOrMany" valueType="String">
      <propertyDefinition href="vocabulary.xml#//@vocabularies[label='Dublin%20Core']/@properties[name='type']"/>
    </resourceProperties>
    <resourceProperties id="_tl7rcCKJEeuEW8NmTOtW7w" name="publisher" valueType="Resource" range="_nr5V8CKJEeuEW8NmTOtW7w"/>
    <configuration xsi:type="oslc4j_ai:MavenSpecificationConfiguration">
      <generalConfiguration filesBasePath="" javaBasePackageName=""/>
      <projectConfiguration xsi:type="oslc4j_ai:MavenProjectConfiguration" doNotGenerateProjectConfigurationFiles="true" lyoVersion="4.0.0-SNAPSHOT" groupId="" artifactId="Dublin Core" version="0.0.1-SNAPSHOT"/>
    </configuration>
  </domainSpecifications>
  <domainSpecifications name="FOAF" namespaceURI="http://xmlns.com/foaf/0.1/#" namespacePrefix="//@domainPrefixes[name='foaf']">
    <resources id="_posq8JUdEeq-KoPaR9_Cfg" name="Person" resourceProperties="_posq8ZUdEeq-KoPaR9_Cfg _posq8pUdEeq-KoPaR9_Cfg _poB8kZUdEeq-KoPaR9_Cfg">
      <describes href="vocabulary.xml#//@vocabularies[label='FOAF']/@classes[name='Person']"/>
    </resources>
    <resources id="_posq85UdEeq-KoPaR9_Cfg" name="Agent" resourceProperties="_poB8kZUdEeq-KoPaR9_Cfg">
      <describes href="vocabulary.xml#//@vocabularies[label='FOAF']/@classes[name='Agent']"/>
    </resources>
    <resourceProperties id="_poB8kZUdEeq-KoPaR9_Cfg" name="name" description="The full name of a person expressed as simple text string." valueType="String">
      <propertyDefinition href="vocabulary.xml#//@vocabularies[label='FOAF']/@properties[name='name']"/>
    </resourceProperties>
    <resourceProperties id="_posq8pUdEeq-KoPaR9_Cfg" name="givenName" description="Given name of person expressed as simple text string. " valueType="String">
      <propertyDefinition href="vocabulary.xml#//@vocabularies[label='FOAF']/@properties[name='givenName']"/>
    </resourceProperties>
    <resourceProperties id="_posq8ZUdEeq-KoPaR9_Cfg" name="familyName" description="Family name of person expressed as simple text string." valueType="String">
      <propertyDefinition href="vocabulary.xml#//@vocabularies[label='FOAF']/@properties[name='familyName']"/>
    </resourceProperties>
  </domainSpecifications>
  <domainSpecifications name="RDF" namespaceURI="http://www.w3.org/1999/02/22-rdf-syntax-ns#" namespacePrefix="//@domainPrefixes[name='rdf']">
    <resourceProperties id="_pnaRgpUdEeq-KoPaR9_Cfg" name="type" description="The resource type URIs" occurs="zeroOrMany" valueType="Resource">
      <propertyDefinition href="vocabulary.xml#//@vocabularies[label='RDF']/@properties[name='type']"/>
    </resourceProperties>
    <resourceProperties id="_poB8kpUdEeq-KoPaR9_Cfg" name="value" occurs="zeroOrOne" valueType="XMLLiteral">
      <propertyDefinition href="vocabulary.xml#//@vocabularies[label='RDF']/@properties[name='value']"/>
    </resourceProperties>
  </domainSpecifications>
  <domainSpecifications name="RDFS" namespaceURI="http://www.w3.org/2000/01/rdf-schema#" namespacePrefix="//@domainPrefixes[name='rdfs']">
    <resources id="_poyKgJUdEeq-KoPaR9_Cfg" name="Class" resourceProperties="_poyxkZUdEeq-KoPaR9_Cfg">
      <describes href="vocabulary.xml#//@vocabularies[label='RDFS']/@classes[name='Class']"/>
    </resources>
    <resourceProperties id="_poyKgZUdEeq-KoPaR9_Cfg" name="member" description="OSLC domains might define a number of member or contains relationships between resources. The rdfs:member property is suitable for use when only one such relationship needs to be defined, or when no additional semantics need to be implied by the property name " valueType="Resource" range="_posq8JUdEeq-KoPaR9_Cfg">
      <propertyDefinition href="vocabulary.xml#//@vocabularies[label='RDFS']/@properties[name='member']"/>
    </resourceProperties>
    <resourceProperties id="_poyxkJUdEeq-KoPaR9_Cfg" name="contains" occurs="zeroOrMany" valueType="Resource"/>
    <resourceProperties id="_posD4ZUdEeq-KoPaR9_Cfg" name="label" description="May be used to provide a human-readable version of a resource's name." occurs="zeroOrOne" valueType="XMLLiteral">
      <propertyDefinition href="vocabulary.xml#//@vocabularies[label='RDFS']/@properties[name='label']"/>
    </resourceProperties>
    <resourceProperties id="_poyxkZUdEeq-KoPaR9_Cfg" name="subClassOf" description="used to state that all the instances of one class are instances of another" valueType="Resource" range="_poyKgJUdEeq-KoPaR9_Cfg">
      <propertyDefinition href="vocabulary.xml#//@vocabularies[label='RDFS']/@properties[name='subClassOf']"/>
    </resourceProperties>
    <resourceProperties id="_posD4JUdEeq-KoPaR9_Cfg" name="comment" description="May be used to provide a human-readable description of a resource." valueType="XMLLiteral">
      <propertyDefinition href="vocabulary.xml#//@vocabularies[label='RDFS']/@properties[name='comment']"/>
    </resourceProperties>
    <resourceProperties id="_poyxkpUdEeq-KoPaR9_Cfg" name="seeAlso" description="Used to indicate a resource that might provide additional information about the subject resource." occurs="zeroOrOne" valueType="URI">
      <propertyDefinition href="vocabulary.xml#//@vocabularies[label='RDFS']/@properties[name='seeAlso']"/>
    </resourceProperties>
    <resourceProperties id="_uuAX4JUdEeq-KoPaR9_Cfg" name="label" valueType="String">
      <propertyDefinition href="vocabulary.xml#//@vocabularies[label='RDFS']/@properties[name='label']"/>
    </resourceProperties>
  </domainSpecifications>
  <domainSpecifications name="OSLC" namespaceURI="http://open-services.net/ns/core#" namespacePrefix="//@domainPrefixes[name='oslc']">
    <resources id="_poPX8JUdEeq-KoPaR9_Cfg" name="ServiceProvider" resourceProperties="_pnZDYJUdEeq-KoPaR9_Cfg _pnXOMpUdEeq-KoPaR9_Cfg _gtmHESKJEeuEW8NmTOtW7w _tl7rcCKJEeuEW8NmTOtW7w"/>
    <resources id="_poPX8ZUdEeq-KoPaR9_Cfg" name="ResourceShape" resourceProperties="_pnZDYJUdEeq-KoPaR9_Cfg _poPX8pUdEeq-KoPaR9_Cfg _poSbQJUdEeq-KoPaR9_Cfg"/>
    <resources id="_poP_AJUdEeq-KoPaR9_Cfg" name="Discussion"/>
    <resources id="_poP_AZUdEeq-KoPaR9_Cfg" name="Property" resourceProperties="_pnXOMpUdEeq-KoPaR9_Cfg _pnZDYJUdEeq-KoPaR9_Cfg _poSbQZUdEeq-KoPaR9_Cfg _poP_ApUdEeq-KoPaR9_Cfg _poP_A5UdEeq-KoPaR9_Cfg _poP_BJUdEeq-KoPaR9_Cfg _poP_BZUdEeq-KoPaR9_Cfg _poQmEJUdEeq-KoPaR9_Cfg _poQmEZUdEeq-KoPaR9_Cfg _poQmEpUdEeq-KoPaR9_Cfg _poQmE5UdEeq-KoPaR9_Cfg _poQmFJUdEeq-KoPaR9_Cfg _poQmFZUdEeq-KoPaR9_Cfg _poRNIJUdEeq-KoPaR9_Cfg _poRNIZUdEeq-KoPaR9_Cfg _poTpYJUdEeq-KoPaR9_Cfg"/>
    <resources id="_poRNIpUdEeq-KoPaR9_Cfg" name="Allowed Values" resourceProperties="_poP_ApUdEeq-KoPaR9_Cfg"/>
    <resources id="_gtmHEiKJEeuEW8NmTOtW7w" name="ServiceProviderCatalog" resourceProperties="_pnZDYJUdEeq-KoPaR9_Cfg _pnXOMpUdEeq-KoPaR9_Cfg _gtmHECKJEeuEW8NmTOtW7w _gtlgACKJEeuEW8NmTOtW7w"/>
    <resources id="_gtmHEyKJEeuEW8NmTOtW7w" name="Service" resourceProperties="_U_N-8CKKEeuEW8NmTOtW7w _U_N-8SKKEeuEW8NmTOtW7w _U_N-8iKKEeuEW8NmTOtW7w _W3oSECKKEeuEW8NmTOtW7w _gtmHECKJEeuEW8NmTOtW7w _jR7PkCKKEeuEW8NmTOtW7w"/>
    <resources id="_nr5V8CKJEeuEW8NmTOtW7w" name="Publisher" resourceProperties="_pnX1QJUdEeq-KoPaR9_Cfg _pnZDYJUdEeq-KoPaR9_Cfg _bLP8ACKNEeuEW8NmTOtW7w"/>
    <resources id="_U_N-8yKKEeuEW8NmTOtW7w" name="CreationFactory" resourceProperties="_pnZDYJUdEeq-KoPaR9_Cfg _K5f2sCKLEeuEW8NmTOtW7w _K5f2sSKLEeuEW8NmTOtW7w _zKmGgCKMEeuEW8NmTOtW7w _jR7PkCKKEeuEW8NmTOtW7w _bLP8ACKNEeuEW8NmTOtW7w"/>
    <resources id="_U_N-9CKKEeuEW8NmTOtW7w" name="QueryCapability" resourceProperties="_pnZDYJUdEeq-KoPaR9_Cfg _zKmGgSKMEeuEW8NmTOtW7w _K5f2sSKLEeuEW8NmTOtW7w _zKmGgCKMEeuEW8NmTOtW7w _jR7PkCKKEeuEW8NmTOtW7w _bLP8ACKNEeuEW8NmTOtW7w"/>
    <resources id="_U_N-9SKKEeuEW8NmTOtW7w" name="Dialog" resourceProperties="_pnZDYJUdEeq-KoPaR9_Cfg _8X71QCKLEeuEW8NmTOtW7w _K5f2sSKLEeuEW8NmTOtW7w _zKmGgCKMEeuEW8NmTOtW7w _jR7PkCKKEeuEW8NmTOtW7w _zKmGgiKMEeuEW8NmTOtW7w _LKVSkCKMEeuEW8NmTOtW7w _bLP8ACKNEeuEW8NmTOtW7w"/>
    <resourceProperties id="_pnZqdJUdEeq-KoPaR9_Cfg" name="serviceProvider" description="A link to the resource's OSLC Service Provider. There may be cases when the subject resource is available from a service provider that implements multiple domain specifications, which could result in multiple values for this property." occurs="zeroOrMany" valueType="Resource" representation="reference"/>
    <resourceProperties id="_pnaRgZUdEeq-KoPaR9_Cfg" name="shortTitle" description="Shorter form of dcterms:title for the resource represented as rich text in XHTML content. SHOULD include only content that is valid inside an XHTML &lt;span> element." occurs="zeroOrOne" valueType="XMLLiteral"/>
    <resourceProperties id="_pnaRgJUdEeq-KoPaR9_Cfg" name="shortId" description="Shorter form of dcterms:identifier for the resource, such as a number." valueType="String"/>
    <resourceProperties id="_pnZqc5UdEeq-KoPaR9_Cfg" name="modifiedBy" description="The URI of a resource describing the entity that most recently modified the subject resource. The link target is usually a foaf:Person or foaf:Agent, but could be any type. This is modeled after dcterms:creator, but Dublin Core currently has no equivalent property." valueType="Resource"/>
    <resourceProperties id="_poPX8pUdEeq-KoPaR9_Cfg" name="describes" description="This shape describes resources that are of any of these types. Formally, a shape S applies to a resource R if there is a triple R rdf:type T and there is a triple S oslc:describes T. " occurs="zeroOrMany" valueType="URI"/>
    <resourceProperties id="_poSbQJUdEeq-KoPaR9_Cfg" name="property" description="The properties that are allowed or required by this shape. " occurs="zeroOrMany" valueType="LocalResource" range="_poP_AZUdEeq-KoPaR9_Cfg"/>
    <resourceProperties id="_poP_ApUdEeq-KoPaR9_Cfg" name="allowedValue" description="value allowed for a property" occurs="oneOrMany" valueType="Resource"/>
    <resourceProperties id="_poSbQZUdEeq-KoPaR9_Cfg" name="allowedValues" description="Resource with allowed values for the property being defined. " valueType="Resource" range="_poRNIpUdEeq-KoPaR9_Cfg"/>
    <resourceProperties id="_poP_A5UdEeq-KoPaR9_Cfg" name="defaultValue" description="A default value for property, inlined into property definition. " occurs="zeroOrOne" valueType="Resource"/>
    <resourceProperties id="_poP_BJUdEeq-KoPaR9_Cfg" name="hidden" description="A hint that indicates that property MAY be hidden when presented in a user interface " occurs="zeroOrOne"/>
    <resourceProperties id="_poP_BZUdEeq-KoPaR9_Cfg" name="isMemberProperty" description="If set to true, this indicates that the property is a membership property, as described in the Query Syntax Specification: Member List Patterns. This is useful when the resource whose shape is being defined is viewed as a container of other resources. For example, look at the last example in Appendix B's RDF/XML Representation Examples: Specifying the shape of a query result, where blog:comment is defined as a membership property and comment that matches the query is returned as value of that property." occurs="zeroOrOne"/>
    <resourceProperties id="_poQmEJUdEeq-KoPaR9_Cfg" name="name" description="Name of property being defined, i.e. second part of property's Prefixed Name" valueType="String"/>
    <resourceProperties id="_poQmEZUdEeq-KoPaR9_Cfg" name="maxSize" description="For String properties only, specifies maximum characters allowed. If not set, then there is no maximum or maximum is specified elsewhere." occurs="zeroOrOne" valueType="Integer"/>
    <resourceProperties id="_poQmEpUdEeq-KoPaR9_Cfg" name="occurs" description="MUST be either http://open-services.net/ns/core#Exactly-one (property is required), http://open-services.net/ns/core#Zero-or-one (property is optional), http://open-services.net/ns/core#zeroOrMany (property is optional), or http://open-services.net/ns/core#One-or-many (property is required)" valueType="Resource"/>
    <resourceProperties id="_poQmE5UdEeq-KoPaR9_Cfg" name="propertyDefinition" description="URI of the property whose usage is being described." valueType="Resource"/>
    <resourceProperties id="_poQmFJUdEeq-KoPaR9_Cfg" name="range" description="For properties with a resource value-type, Providers MAY also specify the range of possible resource types allowed, each specified by URI. The default range is http://open-services.net/ns/core#Any." occurs="zeroOrMany" valueType="Resource"/>
    <resourceProperties id="_poQmFZUdEeq-KoPaR9_Cfg" name="readOnly" description="true if the property is read-only. If omitted, or set to false, then the property is writable. Providers SHOULD declare a property read-only when changes to the value of that property will not be accepted after the resource has been created, e.g. on PUT/PATCH requests. Consumers should note that the converse does not apply: Providers MAY reject a change to the value of a writable property." occurs="zeroOrOne"/>
    <resourceProperties id="_poRNIJUdEeq-KoPaR9_Cfg" name="representation" description="Should be http://open-services.net/ns/core#Reference, http://open-services.net/ns/core#Inline or http://open-services.net/ns/core#Either" occurs="zeroOrOne" valueType="Resource"/>
    <resourceProperties id="_poRNIZUdEeq-KoPaR9_Cfg" name="valueType" description="See below for list of allowed values for oslc:valueType. If this property is omitted, then the value type is unconstrained." occurs="zeroOrMany" valueType="Resource"/>
    <resourceProperties id="_poTpYJUdEeq-KoPaR9_Cfg" name="valueShape" description="if the value-type is a resource type, then Property MAY provide a shape value to indicate the Resource Shape that applies to the resource." valueType="Resource" range="_poPX8ZUdEeq-KoPaR9_Cfg"/>
    <resourceProperties id="_poTpYZUdEeq-KoPaR9_Cfg" name="discussedBy" description="A series of notes and comments about this resource." occurs="zeroOrOne" valueType="Resource" range="_poP_AJUdEeq-KoPaR9_Cfg"/>
    <resourceProperties id="_pnZqcpUdEeq-KoPaR9_Cfg" name="instanceShape" description="The URI of a Resource Shape that describes the possible properties, occurrence, value types, allowed values and labels. This shape information is useful in displaying the subject resource as well as guiding clients in performing modifications. Instance shapes may be specific to the authenticated user associated with the request that retrieved the resource, the current state of the resource and other factors and thus should not be cached." occurs="zeroOrMany" valueType="Resource" representation="reference"/>
    <resourceProperties id="_gtlgACKJEeuEW8NmTOtW7w" name="serviceProvider" occurs="zeroOrMany" valueType="Resource" range="_poPX8JUdEeq-KoPaR9_Cfg"/>
    <resourceProperties id="_gtmHECKJEeuEW8NmTOtW7w" name="domain" occurs="zeroOrMany" valueType="URI"/>
    <resourceProperties id="_gtmHESKJEeuEW8NmTOtW7w" name="service" occurs="zeroOrMany" valueType="Resource" range="_gtmHEyKJEeuEW8NmTOtW7w"/>
    <resourceProperties id="_U_N-8CKKEeuEW8NmTOtW7w" name="creationFactory" valueType="Resource" range="_U_N-8yKKEeuEW8NmTOtW7w"/>
    <resourceProperties id="_U_N-8SKKEeuEW8NmTOtW7w" name="queryCapability" valueType="Resource" range="_U_N-9CKKEeuEW8NmTOtW7w"/>
    <resourceProperties id="_U_N-8iKKEeuEW8NmTOtW7w" name="creationDialog" valueType="Resource" range="_U_N-9SKKEeuEW8NmTOtW7w"/>
    <resourceProperties id="_W3oSECKKEeuEW8NmTOtW7w" name="selectionDialog" valueType="Resource" range="_U_N-9SKKEeuEW8NmTOtW7w"/>
    <resourceProperties id="_jR7PkCKKEeuEW8NmTOtW7w" name="usage" occurs="zeroOrMany" valueType="URI"/>
    <resourceProperties id="_K5f2sCKLEeuEW8NmTOtW7w" name="creation" valueType="URI"/>
    <resourceProperties id="_K5f2sSKLEeuEW8NmTOtW7w" name="resourceShape" occurs="zeroOrMany" valueType="Resource" range="_poPX8ZUdEeq-KoPaR9_Cfg"/>
    <resourceProperties id="_zKmGgCKMEeuEW8NmTOtW7w" name="resourceType" valueType="Resource" range="_poyKgJUdEeq-KoPaR9_Cfg"/>
    <resourceProperties id="_zKmGgSKMEeuEW8NmTOtW7w" name="queryBase" valueType="URI"/>
    <resourceProperties id="_8X71QCKLEeuEW8NmTOtW7w" name="dialog" valueType="URI"/>
    <resourceProperties id="_zKmGgiKMEeuEW8NmTOtW7w" name="hintHeight" occurs="zeroOrOne" valueType="String"/>
    <resourceProperties id="_LKVSkCKMEeuEW8NmTOtW7w" name="hintWidth" occurs="zeroOrOne" valueType="String"/>
    <resourceProperties id="_bLP8ACKNEeuEW8NmTOtW7w" name="label" occurs="zeroOrOne" valueType="String"/>
    <configuration xsi:type="oslc4j_ai:MavenSpecificationConfiguration">
      <generalConfiguration doNotGenerate="true" filesBasePath="" javaBasePackageName="org.eclipse.lyo.oslc4j.core.model"/>
      <projectConfiguration xsi:type="oslc4j_ai:MavenProjectConfiguration" doNotGenerateProjectConfigurationFiles="true" lyoVersion="4.0.0-SNAPSHOT" groupId="org.eclipse.lyo.oslc4j.core.model" artifactId="OSLC" version="0.0.1-SNAPSHOT"/>
    </configuration>
  </domainSpecifications>
  <domainSpecifications name="Change Management shapes" namespaceURI="http://open-services.net/ns/cm#" namespacePrefix="//@domainPrefixes[name='oslc_cm']">
    <resources id="_poJRUJUdEeq-KoPaR9_Cfg" name="ChangeRequest" resourceProperties="_pnaRgZUdEeq-KoPaR9_Cfg _pnXOMpUdEeq-KoPaR9_Cfg _pnZDYJUdEeq-KoPaR9_Cfg _pnX1QJUdEeq-KoPaR9_Cfg _pnYcUZUdEeq-KoPaR9_Cfg _pna4kJUdEeq-KoPaR9_Cfg _pna4kZUdEeq-KoPaR9_Cfg _pnXOMZUdEeq-KoPaR9_Cfg _pnYcUJUdEeq-KoPaR9_Cfg _pnZqdJUdEeq-KoPaR9_Cfg _pnZqcpUdEeq-KoPaR9_Cfg _poTpYZUdEeq-KoPaR9_Cfg _poJ4YJUdEeq-KoPaR9_Cfg _poJ4YZUdEeq-KoPaR9_Cfg _poJ4YpUdEeq-KoPaR9_Cfg _poJ4Y5UdEeq-KoPaR9_Cfg _poKfcJUdEeq-KoPaR9_Cfg _poKfcZUdEeq-KoPaR9_Cfg _poKfcpUdEeq-KoPaR9_Cfg _poKfc5UdEeq-KoPaR9_Cfg _poKfdJUdEeq-KoPaR9_Cfg _poKfdZUdEeq-KoPaR9_Cfg _poNiwJUdEeq-KoPaR9_Cfg _poKfeJUdEeq-KoPaR9_Cfg _poLGgJUdEeq-KoPaR9_Cfg _poLGgZUdEeq-KoPaR9_Cfg _poKfd5UdEeq-KoPaR9_Cfg _poOJ0JUdEeq-KoPaR9_Cfg _poOJ0ZUdEeq-KoPaR9_Cfg _poOJ0pUdEeq-KoPaR9_Cfg _poKfdpUdEeq-KoPaR9_Cfg">
      <describes href="vocabulary.xml#//@vocabularies[label='Change%20Management%20vocab']/@classes[name='ChangeRequest']"/>
    </resources>
    <resources id="_poLGgpUdEeq-KoPaR9_Cfg" name="Defect" extends="_poJRUJUdEeq-KoPaR9_Cfg">
      <describes href="vocabulary.xml#//@vocabularies[label='Change%20Management%20vocab']/@classes[name='Defect']"/>
    </resources>
    <resources id="_poLtkJUdEeq-KoPaR9_Cfg" name="Priority">
      <describes href="vocabulary.xml#//@vocabularies[label='Change%20Management%20vocab']/@classes[name='Priority']"/>
    </resources>
    <resources id="_poLtkZUdEeq-KoPaR9_Cfg" name="State"/>
    <resources id="_poLtkpUdEeq-KoPaR9_Cfg" name="ChangeNotice" extends="_poJRUJUdEeq-KoPaR9_Cfg">
      <describes href="vocabulary.xml#//@vocabularies[label='Change%20Management%20vocab']/@classes[name='ChangeNotice']"/>
    </resources>
    <resources id="_poLtk5UdEeq-KoPaR9_Cfg" name="Task" extends="_poJRUJUdEeq-KoPaR9_Cfg">
      <describes href="vocabulary.xml#//@vocabularies[label='Change%20Management%20vocab']/@classes[name='Task']"/>
    </resources>
    <resources id="_poMUoJUdEeq-KoPaR9_Cfg" name="ReviewTask" extends="_poLtk5UdEeq-KoPaR9_Cfg">
      <describes href="vocabulary.xml#//@vocabularies[label='Change%20Management%20vocab']/@classes[name='ReviewTask']"/>
    </resources>
    <resources id="_poMUoZUdEeq-KoPaR9_Cfg" name="Enhancement" extends="_poJRUJUdEeq-KoPaR9_Cfg">
      <describes href="vocabulary.xml#//@vocabularies[label='Change%20Management%20vocab']/@classes[name='Enhancement']"/>
    </resources>
    <resourceProperties id="_poJ4YJUdEeq-KoPaR9_Cfg" name="closeDate" description="The date at which no further activity or work is intended to be conducted." occurs="zeroOrOne" valueType="DateTime">
      <propertyDefinition href="vocabulary.xml#//@vocabularies[label='Change%20Management%20vocab']/@properties[name='closeDate']"/>
    </resourceProperties>
    <resourceProperties id="_poJ4YZUdEeq-KoPaR9_Cfg" name="status" description="Used to indicate the status of the change request based on values defined by the service provider. Most often a read-only property. Some possible values may include: 'Submitted', 'Done', 'InProgress', etc." occurs="zeroOrOne" valueType="String">
      <propertyDefinition href="vocabulary.xml#//@vocabularies[label='Change%20Management%20vocab']/@properties[name='status']"/>
    </resourceProperties>
    <resourceProperties id="_poJ4YpUdEeq-KoPaR9_Cfg" name="closed" description="Whether or not the Change Request is completely done, no further fixes or fix verification is needed." occurs="zeroOrOne">
      <propertyDefinition href="vocabulary.xml#//@vocabularies[label='Change%20Management%20vocab']/@properties[name='closed']"/>
    </resourceProperties>
    <resourceProperties id="_poJ4Y5UdEeq-KoPaR9_Cfg" name="inProgress" description="Whether or not the Change Request in a state indicating that active work is occurring. If oslc_cm:inprogress is true, then oslc_cm:fixed and oslc_cm:closed must also be false" occurs="zeroOrOne"/>
    <resourceProperties id="_poKfcJUdEeq-KoPaR9_Cfg" name="fixed" description="Whether or not the Change Request has been fixed." occurs="zeroOrOne">
      <propertyDefinition href="vocabulary.xml#//@vocabularies[label='Change%20Management%20vocab']/@properties[name='fixed']"/>
    </resourceProperties>
    <resourceProperties id="_poKfcZUdEeq-KoPaR9_Cfg" name="approved" description="Whether or not the Change Request has been approved." occurs="zeroOrOne" representation="either"/>
    <resourceProperties id="_poKfcpUdEeq-KoPaR9_Cfg" name="reviewed" description="Whether or not the Change Request has been reviewed." occurs="zeroOrOne">
      <propertyDefinition href="vocabulary.xml#//@vocabularies[label='Change%20Management%20vocab']/@properties[name='reviewed']"/>
    </resourceProperties>
    <resourceProperties id="_poKfc5UdEeq-KoPaR9_Cfg" name="verified" description="Whether or not the resolution or fix of the Change Request has been verified." occurs="zeroOrOne">
      <propertyDefinition href="vocabulary.xml#//@vocabularies[label='Change%20Management%20vocab']/@properties[name='verified']"/>
    </resourceProperties>
    <resourceProperties id="_poKfdJUdEeq-KoPaR9_Cfg" name="relatedChangeRequest" description="This relationship is loosely coupled and has no specific meaning. It is likely that the target resource will be an oslc_cm:ChangeRequest but that is not necessarily the case." occurs="zeroOrMany" valueType="Resource" representation="reference">
      <propertyDefinition href="vocabulary.xml#//@vocabularies[label='Change%20Management%20vocab']/@properties[name='relatedChangeRequest']"/>
    </resourceProperties>
    <resourceProperties id="_poKfdZUdEeq-KoPaR9_Cfg" name="affectsPlanItem" description="Change request affects a plan item. It is likely that the target resource will be an oslc_cm:ChangeRequest but that is not necessarily the case." occurs="zeroOrMany" valueType="Resource" representation="reference">
      <propertyDefinition href="vocabulary.xml#//@vocabularies[label='Change%20Management%20vocab']/@properties[name='affectsPlanItem']"/>
    </resourceProperties>
    <resourceProperties id="_poNiwJUdEeq-KoPaR9_Cfg" name="affectedByDefect" description="Change request is affected by a reported defect. It is likely that the target resource will be an oslc_cm:ChangeRequest but that is not necessarily the case." occurs="zeroOrMany" valueType="Resource" range="_poLGgpUdEeq-KoPaR9_Cfg" representation="reference">
      <propertyDefinition href="vocabulary.xml#//@vocabularies[label='Change%20Management%20vocab']/@properties[name='affectedByDefect']"/>
    </resourceProperties>
    <resourceProperties id="_poKfeJUdEeq-KoPaR9_Cfg" name="tracksRequirement" description="Tracks the associated Requirement or Requirement ChangeSet resources. It is likely that the target resource will be an oslc_rm:Requirement but that is not necessarily the case." occurs="zeroOrMany" valueType="Resource" range="_pnz6IJUdEeq-KoPaR9_Cfg"/>
    <resourceProperties id="_poLGgJUdEeq-KoPaR9_Cfg" name="implementsRequirement" description="Implements associated Requirement. It is likely that the target resource will be an oslc_rm:Requirement but that is not necessarily the case." occurs="zeroOrMany" valueType="Resource" range="_pnz6IJUdEeq-KoPaR9_Cfg" representation="reference">
      <propertyDefinition href="vocabulary.xml#//@vocabularies[label='Change%20Management%20vocab']/@properties[name='implementsRequirement']"/>
    </resourceProperties>
    <resourceProperties id="_poLGgZUdEeq-KoPaR9_Cfg" name="affectsRequirement" description="Change request affecting a Requirement. It is likely that the target resource will be an oslc_rm:Requirement but that is not necessarily the case." occurs="zeroOrMany" valueType="Resource" range="_pnz6IJUdEeq-KoPaR9_Cfg" representation="reference">
      <propertyDefinition href="vocabulary.xml#//@vocabularies[label='Change%20Management%20vocab']/@properties[name='affectsRequirement']"/>
    </resourceProperties>
    <resourceProperties id="_poKfd5UdEeq-KoPaR9_Cfg" name="tracksChangeSet" description="Tracks SCM change set resource. It is likely that the target resource will be an oslc_scm:ChangeSet but that is not necessarily the case." occurs="zeroOrMany" valueType="Resource" range="_pna4kpUdEeq-KoPaR9_Cfg" representation="reference"/>
    <resourceProperties id="_poOJ0JUdEeq-KoPaR9_Cfg" name="parent" occurs="zeroOrMany" valueType="Resource" range="_poJRUJUdEeq-KoPaR9_Cfg" representation="either">
      <propertyDefinition href="vocabulary.xml#//@vocabularies[label='Change%20Management%20vocab']/@properties[name='parent']"/>
    </resourceProperties>
    <resourceProperties id="_poOJ0ZUdEeq-KoPaR9_Cfg" name="priority" occurs="zeroOrMany" valueType="Resource" range="_poLtkJUdEeq-KoPaR9_Cfg" representation="either"/>
    <resourceProperties id="_poOJ0pUdEeq-KoPaR9_Cfg" name="state" occurs="zeroOrOne" valueType="Resource" range="_poLtkZUdEeq-KoPaR9_Cfg" representation="either">
      <propertyDefinition href="vocabulary.xml#//@vocabularies[label='Change%20Management%20vocab']/@properties[name='state']"/>
    </resourceProperties>
    <resourceProperties id="_poKfdpUdEeq-KoPaR9_Cfg" name="authorizer" occurs="zeroOrMany" valueType="Resource" range="_posq85UdEeq-KoPaR9_Cfg"/>
    <configuration xsi:type="oslc4j_ai:MavenSpecificationConfiguration">
      <generalConfiguration filesBasePath="" javaBasePackageName="org.eclipse.lyo.oslc.domains.cm"/>
      <projectConfiguration xsi:type="oslc4j_ai:MavenProjectConfiguration" doNotGenerateProjectConfigurationFiles="true" lyoVersion="4.0.0-SNAPSHOT" groupId="org.eclipse.lyo.oslc.domains.cm" artifactId="Change Management shapes" version="0.0.1-SNAPSHOT"/>
    </configuration>
  </domainSpecifications>
  <domainSpecifications name="Requirements Management shapes" namespaceURI="http://open-services.net/ns/rm#" namespacePrefix="//@domainPrefixes[name='oslc_rm']">
    <resources id="_pnz6IJUdEeq-KoPaR9_Cfg" name="Requirement" resourceProperties="_pnZDYJUdEeq-KoPaR9_Cfg _pnXOMpUdEeq-KoPaR9_Cfg _pnX1QJUdEeq-KoPaR9_Cfg _pnaRgZUdEeq-KoPaR9_Cfg _pnYcUZUdEeq-KoPaR9_Cfg _pna4kJUdEeq-KoPaR9_Cfg _pna4kZUdEeq-KoPaR9_Cfg _pnXOMZUdEeq-KoPaR9_Cfg _pnYcUJUdEeq-KoPaR9_Cfg _pnZqdJUdEeq-KoPaR9_Cfg _pnZqcpUdEeq-KoPaR9_Cfg _pn0hMJUdEeq-KoPaR9_Cfg _pn1IQJUdEeq-KoPaR9_Cfg _pn1IQZUdEeq-KoPaR9_Cfg _pn1IQpUdEeq-KoPaR9_Cfg _pn1IQ5UdEeq-KoPaR9_Cfg _pn1IRJUdEeq-KoPaR9_Cfg _pn1IRZUdEeq-KoPaR9_Cfg _pn1vUJUdEeq-KoPaR9_Cfg _pn1vUZUdEeq-KoPaR9_Cfg _pn1vUpUdEeq-KoPaR9_Cfg _pn1vU5UdEeq-KoPaR9_Cfg _pn1vVJUdEeq-KoPaR9_Cfg _pn1vVZUdEeq-KoPaR9_Cfg _pn2WYJUdEeq-KoPaR9_Cfg">
      <describes href="vocabulary.xml#//@vocabularies[label='Requirements%20Management%20vocabulary']/@classes[name='Requirement']"/>
    </resources>
    <resources id="_pn2WYZUdEeq-KoPaR9_Cfg" name="RequirementCollection" resourceProperties="_pnZDYJUdEeq-KoPaR9_Cfg _pnXOMpUdEeq-KoPaR9_Cfg _pnX1QJUdEeq-KoPaR9_Cfg _pnaRgZUdEeq-KoPaR9_Cfg _pnYcUZUdEeq-KoPaR9_Cfg _pna4kJUdEeq-KoPaR9_Cfg _pna4kZUdEeq-KoPaR9_Cfg _pnXOMZUdEeq-KoPaR9_Cfg _pnYcUJUdEeq-KoPaR9_Cfg _pnZqdJUdEeq-KoPaR9_Cfg _pnZqcpUdEeq-KoPaR9_Cfg _pn0hMJUdEeq-KoPaR9_Cfg _pn1IQJUdEeq-KoPaR9_Cfg _pn1IQZUdEeq-KoPaR9_Cfg _pn1IQpUdEeq-KoPaR9_Cfg _pn1IQ5UdEeq-KoPaR9_Cfg _pn1IRJUdEeq-KoPaR9_Cfg _pn1IRZUdEeq-KoPaR9_Cfg _pn1vUJUdEeq-KoPaR9_Cfg _pn1vUZUdEeq-KoPaR9_Cfg _pn1vUpUdEeq-KoPaR9_Cfg _pn1vU5UdEeq-KoPaR9_Cfg _pn1vVJUdEeq-KoPaR9_Cfg _pn1vVZUdEeq-KoPaR9_Cfg _pn2WYJUdEeq-KoPaR9_Cfg _pn4yoJUdEeq-KoPaR9_Cfg">
      <describes href="vocabulary.xml#//@vocabularies[label='Requirements%20Management%20vocabulary']/@classes[name='RequirementCollection']"/>
    </resources>
    <resourceProperties id="_pn0hMJUdEeq-KoPaR9_Cfg" name="elaboratedBy" description="The subject is elaborated by the object. For example, a user requirement is elaborated by use case." occurs="zeroOrMany" valueType="Resource" representation="reference">
      <propertyDefinition href="vocabulary.xml#//@vocabularies[label='Requirements%20Management%20vocabulary']/@properties[name='elaboratedBy']"/>
    </resourceProperties>
    <resourceProperties id="_pn1IQJUdEeq-KoPaR9_Cfg" name="elaborates" description="The object is elaborated by the subject." occurs="zeroOrMany" valueType="Resource" representation="reference">
      <propertyDefinition href="vocabulary.xml#//@vocabularies[label='Requirements%20Management%20vocabulary']/@properties[name='elaborates']"/>
    </resourceProperties>
    <resourceProperties id="_pn1IQZUdEeq-KoPaR9_Cfg" name="specifiedBy" description="The subject is specified by the object. For example, a requirement is elaborated by a model element ." occurs="zeroOrMany" valueType="Resource" representation="reference">
      <propertyDefinition href="vocabulary.xml#//@vocabularies[label='Requirements%20Management%20vocabulary']/@properties[name='specifiedBy']"/>
    </resourceProperties>
    <resourceProperties id="_pn1IQpUdEeq-KoPaR9_Cfg" name="specifies" description="The object is specified by the subject." occurs="zeroOrMany" valueType="Resource" representation="reference">
      <propertyDefinition href="vocabulary.xml#//@vocabularies[label='Requirements%20Management%20vocabulary']/@properties[name='specifies']"/>
    </resourceProperties>
    <resourceProperties id="_pn1IQ5UdEeq-KoPaR9_Cfg" name="affectedBy" description="Requirement is affected by a resource, such as a defect or issue." occurs="zeroOrMany" valueType="Resource" representation="reference">
      <propertyDefinition href="vocabulary.xml#//@vocabularies[label='Requirements%20Management%20vocabulary']/@properties[name='affectedBy']"/>
    </resourceProperties>
    <resourceProperties id="_pn1IRJUdEeq-KoPaR9_Cfg" name="trackedBy" description="Resource, such as a change request, which tracks this requirement." occurs="zeroOrMany" valueType="Resource" representation="reference">
      <propertyDefinition href="vocabulary.xml#//@vocabularies[label='Requirements%20Management%20vocabulary']/@properties[name='trackedBy']"/>
    </resourceProperties>
    <resourceProperties id="_pn1IRZUdEeq-KoPaR9_Cfg" name="implementedBy" description="Resource, such as a change request, which implements this requirement." occurs="zeroOrMany" valueType="Resource" representation="reference">
      <propertyDefinition href="vocabulary.xml#//@vocabularies[label='Requirements%20Management%20vocabulary']/@properties[name='implementedBy']"/>
    </resourceProperties>
    <resourceProperties id="_pn1vUJUdEeq-KoPaR9_Cfg" name="validatedBy" description="Resource, such as a test case, which validates this requirement." occurs="zeroOrMany" valueType="Resource" representation="reference">
      <propertyDefinition href="vocabulary.xml#//@vocabularies[label='Requirements%20Management%20vocabulary']/@properties[name='validatedBy']"/>
    </resourceProperties>
    <resourceProperties id="_pn1vUZUdEeq-KoPaR9_Cfg" name="satisfiedBy" description="The subject is satisfied by the object. For example, a user requirement is satisfied by a system requirement." occurs="zeroOrMany" valueType="Resource" representation="reference">
      <propertyDefinition href="vocabulary.xml#//@vocabularies[label='Requirements%20Management%20vocabulary']/@properties[name='satisfiedBy']"/>
    </resourceProperties>
    <resourceProperties id="_pn1vUpUdEeq-KoPaR9_Cfg" name="satisfies" description="The object is satisfied by the subject." occurs="zeroOrMany" valueType="Resource" representation="reference">
      <propertyDefinition href="vocabulary.xml#//@vocabularies[label='Requirements%20Management%20vocabulary']/@properties[name='satisfies']"/>
    </resourceProperties>
    <resourceProperties id="_pn1vU5UdEeq-KoPaR9_Cfg" name="decomposedBy" description="The subject is decomposed by the object. For example, a system requirement is decomposed into a collection of system requirements." occurs="zeroOrMany" valueType="Resource" representation="reference">
      <propertyDefinition href="vocabulary.xml#//@vocabularies[label='Requirements%20Management%20vocabulary']/@properties[name='decomposedBy']"/>
    </resourceProperties>
    <resourceProperties id="_pn1vVJUdEeq-KoPaR9_Cfg" name="decomposes" description="The object is decomposed by the subject." occurs="zeroOrMany" valueType="Resource" representation="reference">
      <propertyDefinition href="vocabulary.xml#//@vocabularies[label='Requirements%20Management%20vocabulary']/@properties[name='decomposes']"/>
    </resourceProperties>
    <resourceProperties id="_pn1vVZUdEeq-KoPaR9_Cfg" name="constrainedBy" description="The subject is constrained by the object. For example, a functional requirement is constrained by a safety requirement." occurs="zeroOrMany" valueType="Resource" representation="reference">
      <propertyDefinition href="vocabulary.xml#//@vocabularies[label='Requirements%20Management%20vocabulary']/@properties[name='constrainedBy']"/>
    </resourceProperties>
    <resourceProperties id="_pn2WYJUdEeq-KoPaR9_Cfg" name="constrains" description="The object is constrained by the subject." occurs="zeroOrMany" valueType="Resource" representation="reference">
      <propertyDefinition href="vocabulary.xml#//@vocabularies[label='Requirements%20Management%20vocabulary']/@properties[name='constrains']"/>
    </resourceProperties>
    <resourceProperties id="_pn4yoJUdEeq-KoPaR9_Cfg" title="" name="uses" description="A collection uses a resource - the resource is in the requirement collection. " occurs="zeroOrMany" valueType="Resource" representation="reference">
      <propertyDefinition href="vocabulary.xml#//@vocabularies[label='Requirements%20Management%20vocabulary']/@properties[name='uses']"/>
    </resourceProperties>
    <configuration xsi:type="oslc4j_ai:MavenSpecificationConfiguration">
      <generalConfiguration filesBasePath="" javaBasePackageName="org.eclipse.lyo.oslc.domains.rm"/>
      <projectConfiguration xsi:type="oslc4j_ai:MavenProjectConfiguration" doNotGenerateProjectConfigurationFiles="true" lyoVersion="4.0.0-SNAPSHOT" groupId="org.eclipse.lyo.oslc.domains.rm" artifactId="Requirements Management shapes" version="0.0.1-SNAPSHOT"/>
    </configuration>
  </domainSpecifications>
  <domainSpecifications name="Quality Management" namespaceURI="http://open-services.net/ns/qm#" namespacePrefix="//@domainPrefixes[name='oslc_qm']">
    <resources id="_pofPkJUdEeq-KoPaR9_Cfg" name="TestPlan" resourceProperties="_pna4kZUdEeq-KoPaR9_Cfg _pnXOMZUdEeq-KoPaR9_Cfg _pna4kJUdEeq-KoPaR9_Cfg _pnXOMpUdEeq-KoPaR9_Cfg _pnX1QJUdEeq-KoPaR9_Cfg _pnYcUJUdEeq-KoPaR9_Cfg _pnYcUZUdEeq-KoPaR9_Cfg _pnZDYJUdEeq-KoPaR9_Cfg _pnaRgpUdEeq-KoPaR9_Cfg _pnZqcpUdEeq-KoPaR9_Cfg _pnZqdJUdEeq-KoPaR9_Cfg _polWMZUdEeq-KoPaR9_Cfg _pogdsJUdEeq-KoPaR9_Cfg _pogdsZUdEeq-KoPaR9_Cfg">
      <describes href="vocabulary.xml#//@vocabularies[label='Quality%20Management']/@classes[name='TestPlan']"/>
    </resources>
    <resources id="_pogdspUdEeq-KoPaR9_Cfg" name="TestCase" resourceProperties="_pna4kZUdEeq-KoPaR9_Cfg _pnXOMZUdEeq-KoPaR9_Cfg _pna4kJUdEeq-KoPaR9_Cfg _pnXOMpUdEeq-KoPaR9_Cfg _pnX1QJUdEeq-KoPaR9_Cfg _pnYcUJUdEeq-KoPaR9_Cfg _pnZqcpUdEeq-KoPaR9_Cfg _pnZqdJUdEeq-KoPaR9_Cfg _pnYcUZUdEeq-KoPaR9_Cfg _pnZDYJUdEeq-KoPaR9_Cfg _pnaRgpUdEeq-KoPaR9_Cfg _pogdsZUdEeq-KoPaR9_Cfg _pohr0JUdEeq-KoPaR9_Cfg _pol9QJUdEeq-KoPaR9_Cfg _pohr0ZUdEeq-KoPaR9_Cfg">
      <describes href="vocabulary.xml#//@vocabularies[label='Quality%20Management']/@classes[name='TestCase']"/>
    </resources>
    <resources id="_poiS4JUdEeq-KoPaR9_Cfg" name="TestExecutionRecord" resourceProperties="_pna4kZUdEeq-KoPaR9_Cfg _pnXOMZUdEeq-KoPaR9_Cfg _pna4kJUdEeq-KoPaR9_Cfg _pnX1QJUdEeq-KoPaR9_Cfg _pnYcUJUdEeq-KoPaR9_Cfg _pnaRgpUdEeq-KoPaR9_Cfg _pnZqcpUdEeq-KoPaR9_Cfg _pnZqdJUdEeq-KoPaR9_Cfg _pnZDYJUdEeq-KoPaR9_Cfg _poi58ZUdEeq-KoPaR9_Cfg _pogdsZUdEeq-KoPaR9_Cfg _pol9QZUdEeq-KoPaR9_Cfg _poi58JUdEeq-KoPaR9_Cfg _pol9QpUdEeq-KoPaR9_Cfg">
      <describes href="vocabulary.xml#//@vocabularies[label='Quality%20Management']/@classes[name='TestExecutionRecord']"/>
    </resources>
    <resources id="_pojhAJUdEeq-KoPaR9_Cfg" name="TestScript" resourceProperties="_pna4kZUdEeq-KoPaR9_Cfg _pnXOMZUdEeq-KoPaR9_Cfg _pna4kJUdEeq-KoPaR9_Cfg _pnXOMpUdEeq-KoPaR9_Cfg _pnX1QJUdEeq-KoPaR9_Cfg _pnYcUJUdEeq-KoPaR9_Cfg _pnZqcpUdEeq-KoPaR9_Cfg _pnZqdJUdEeq-KoPaR9_Cfg _pnZDYJUdEeq-KoPaR9_Cfg _pnaRgpUdEeq-KoPaR9_Cfg _pokIEJUdEeq-KoPaR9_Cfg _pogdsZUdEeq-KoPaR9_Cfg _pohr0ZUdEeq-KoPaR9_Cfg">
      <describes href="vocabulary.xml#//@vocabularies[label='Quality%20Management']/@classes[name='TestScript']"/>
    </resources>
    <resources id="_pokIEZUdEeq-KoPaR9_Cfg" name="TestResult" resourceProperties="_pnXOMZUdEeq-KoPaR9_Cfg _pnX1QJUdEeq-KoPaR9_Cfg _pnYcUJUdEeq-KoPaR9_Cfg _pnZqcpUdEeq-KoPaR9_Cfg _pnZDYJUdEeq-KoPaR9_Cfg _pnaRgpUdEeq-KoPaR9_Cfg _pnZqdJUdEeq-KoPaR9_Cfg _pokvIJUdEeq-KoPaR9_Cfg _polWMJUdEeq-KoPaR9_Cfg _pol9Q5UdEeq-KoPaR9_Cfg _pomkUJUdEeq-KoPaR9_Cfg _pomkUZUdEeq-KoPaR9_Cfg _pol9QZUdEeq-KoPaR9_Cfg">
      <describes href="vocabulary.xml#//@vocabularies[label='Quality%20Management']/@classes[name='TestResult']"/>
    </resources>
    <resourceProperties id="_pogdsZUdEeq-KoPaR9_Cfg" name="relatedChangeRequest" description="A related change request. It is likely that the target resource will be an oslc_cm:ChangeRequest but that is not necessarily the case." occurs="zeroOrMany" valueType="Resource" range="_poJRUJUdEeq-KoPaR9_Cfg" representation="reference">
      <propertyDefinition href="vocabulary.xml#//@vocabularies[label='Quality%20Management']/@properties[name='relatedChangeRequest']"/>
    </resourceProperties>
    <resourceProperties id="_polWMZUdEeq-KoPaR9_Cfg" name="usesTestCase" description="Test Case used by the Test Plan. It is likely that the target resource will be an oslc_qm:TestCase but that is not necessarily the case." occurs="zeroOrMany" valueType="Resource" range="_pogdspUdEeq-KoPaR9_Cfg" representation="either">
      <propertyDefinition href="vocabulary.xml#//@vocabularies[label='Quality%20Management']/@properties[name='usesTestCase']"/>
    </resourceProperties>
    <resourceProperties id="_pogdsJUdEeq-KoPaR9_Cfg" name="validatesRequirementCollection" description="Requirement Collection that is validated by the Test Plan. It is likely that the target resource will be an oslc_rm:RequirementCollection but that is not necessarily the case." occurs="zeroOrMany" valueType="Resource" range="_pn2WYZUdEeq-KoPaR9_Cfg" representation="reference">
      <propertyDefinition href="vocabulary.xml#//@vocabularies[label='Quality%20Management']/@properties[name='validatesRequirementCollection']"/>
    </resourceProperties>
    <resourceProperties id="_pohr0JUdEeq-KoPaR9_Cfg" name="testsChangeRequest" description="Change Request tested by the Test Case. It is likely that the target resource will be an oslc_cm:ChangeRequest but that is not necessarily the case." occurs="zeroOrMany" valueType="Resource" range="_poJRUJUdEeq-KoPaR9_Cfg" representation="reference">
      <propertyDefinition href="vocabulary.xml#//@vocabularies[label='Quality%20Management']/@properties[name='testsChangeRequest']"/>
    </resourceProperties>
    <resourceProperties id="_pol9QJUdEeq-KoPaR9_Cfg" name="usesTestScript" description="Test Script used by the Test Case. It is likely that the target resource will be an oslc_qm:TestScript but that is not necessarily the case." occurs="oneOrMany" valueType="Resource" range="_pojhAJUdEeq-KoPaR9_Cfg" representation="either">
      <propertyDefinition href="vocabulary.xml#//@vocabularies[label='Quality%20Management']/@properties[name='usesTestScript']"/>
    </resourceProperties>
    <resourceProperties id="_pohr0ZUdEeq-KoPaR9_Cfg" name="validatesRequirement" description="Requirement that is validated by the Test Case. It is likely that the target resource will be an oslc_rm:Requirement but that is not necessarily the case." occurs="zeroOrMany" valueType="Resource" range="_pnz6IJUdEeq-KoPaR9_Cfg" representation="reference">
      <propertyDefinition href="vocabulary.xml#//@vocabularies[label='Quality%20Management']/@properties[name='validatesRequirement']"/>
    </resourceProperties>
    <resourceProperties id="_pokIEJUdEeq-KoPaR9_Cfg" name="executionInstructions" description="Instructions for executing the test script. Note that the value of Occurs is undefined. The resource shape document provided by the QM service provider may be consulted for its value." occurs="zeroOrMany" valueType="Resource" representation="reference">
      <propertyDefinition href="vocabulary.xml#//@vocabularies[label='Quality%20Management']/@properties[name='executionInstructions']"/>
    </resourceProperties>
    <resourceProperties id="_poi58ZUdEeq-KoPaR9_Cfg" name="blockedByChangeRequest" description="Change Request that prevents execution of the Test Execution Record. It is likely that the target resource will be an oslc_cm:ChangeRequest but that is not necessarily the case." occurs="zeroOrMany" valueType="Resource" range="_poJRUJUdEeq-KoPaR9_Cfg" representation="reference">
      <propertyDefinition href="vocabulary.xml#//@vocabularies[label='Quality%20Management']/@properties[name='blockedByChangeRequest']"/>
    </resourceProperties>
    <resourceProperties id="_poi58JUdEeq-KoPaR9_Cfg" name="runsOnTestEnvironment" description="Indicates the environment details of the test case for this execution record." occurs="zeroOrOne" valueType="Resource" representation="reference">
      <propertyDefinition href="vocabulary.xml#//@vocabularies[label='Quality%20Management']/@properties[name='runsOnTestEnvironment']"/>
    </resourceProperties>
    <resourceProperties id="_pol9QZUdEeq-KoPaR9_Cfg" name="reportsOnTestPlan" description="Test Plan that the Test Execution Record reports on. It is likely that the target resource will be an oslc_qm:TestPlan but that is not necessarily the case." occurs="zeroOrOne" valueType="Resource" range="_pofPkJUdEeq-KoPaR9_Cfg" representation="either">
      <propertyDefinition href="vocabulary.xml#//@vocabularies[label='Quality%20Management']/@properties[name='reportsOnTestPlan']"/>
    </resourceProperties>
    <resourceProperties id="_pol9QpUdEeq-KoPaR9_Cfg" name="runsTestCase" description="Test Case run by the Test Execution Record. It is likely that the target resource will be an oslc_qm:TestCase but that is not necessarily the case." valueType="Resource" range="_pogdspUdEeq-KoPaR9_Cfg" representation="either">
      <propertyDefinition href="vocabulary.xml#//@vocabularies[label='Quality%20Management']/@properties[name='runsTestCase']"/>
    </resourceProperties>
    <resourceProperties id="_pokvIJUdEeq-KoPaR9_Cfg" name="status" description="Used to indicate the state of the Test Result based on values defined by the service provider. Most often a read-only property." occurs="zeroOrOne" valueType="String"/>
    <resourceProperties id="_polWMJUdEeq-KoPaR9_Cfg" name="affectedByChangeRequest" description="Change request that affects the Test Result. It is likely that the target resource will be an oslc_cm:ChangeRequest but that is not necessarily the case." occurs="zeroOrMany" valueType="Resource" range="_poJRUJUdEeq-KoPaR9_Cfg" representation="reference">
      <propertyDefinition href="vocabulary.xml#//@vocabularies[label='Quality%20Management']/@properties[name='affectedByChangeRequest']"/>
    </resourceProperties>
    <resourceProperties id="_pol9Q5UdEeq-KoPaR9_Cfg" title="" name="executesTestScript" description="Test Script executed to produce the Test Result. It is likely that the target resource will be an oslc_qm:TestScript but that is not necessarily the case." occurs="zeroOrOne" valueType="Resource" range="_pojhAJUdEeq-KoPaR9_Cfg" representation="either">
      <propertyDefinition href="vocabulary.xml#//@vocabularies[label='Quality%20Management']/@properties[name='executesTestScript']"/>
    </resourceProperties>
    <resourceProperties id="_pomkUJUdEeq-KoPaR9_Cfg" title="" name="producedByTestExecutionRecord" description="Test Execution Record that the Test Result was produced by. It is likely that the target resource will be an oslc_qm:TestExecutionRecord but that is not necessarily the case." occurs="zeroOrOne" valueType="Resource" range="_poiS4JUdEeq-KoPaR9_Cfg" representation="either">
      <propertyDefinition href="vocabulary.xml#//@vocabularies[label='Quality%20Management']/@properties[name='producedByTestExecutionRecord']"/>
    </resourceProperties>
    <resourceProperties id="_pomkUZUdEeq-KoPaR9_Cfg" name="reportsOnTestCase" description="Test Case that the Test Result reports on. It is likely that the target resource will be an oslc_qm:TestCase but that is not necessarily the case." valueType="Resource" range="_pogdspUdEeq-KoPaR9_Cfg" representation="either">
      <propertyDefinition href="vocabulary.xml#//@vocabularies[label='Quality%20Management']/@properties[name='reportsOnTestCase']"/>
    </resourceProperties>
    <configuration xsi:type="oslc4j_ai:MavenSpecificationConfiguration">
      <generalConfiguration filesBasePath="" javaBasePackageName="org.eclipse.lyo.oslc.domains.qm"/>
      <projectConfiguration xsi:type="oslc4j_ai:MavenProjectConfiguration" doNotGenerateProjectConfigurationFiles="true" lyoVersion="4.0.0-SNAPSHOT" groupId="org.eclipse.lyo.oslc.domains.qm" artifactId="Quality Management" version="0.0.1-SNAPSHOT"/>
    </configuration>
  </domainSpecifications>
  <domainSpecifications name="Architecture Management" namespaceURI="http://open-services.net/ns/am#" namespacePrefix="//@domainPrefixes[name='oslc_am']">
    <resources id="_popnoJUdEeq-KoPaR9_Cfg" name="Resource" resourceProperties="_pna4kZUdEeq-KoPaR9_Cfg _pnXOMZUdEeq-KoPaR9_Cfg _pna4kJUdEeq-KoPaR9_Cfg _pnXOMpUdEeq-KoPaR9_Cfg _pnX1QJUdEeq-KoPaR9_Cfg _pnYcUJUdEeq-KoPaR9_Cfg _poqOsJUdEeq-KoPaR9_Cfg _pnZDYJUdEeq-KoPaR9_Cfg _poqOsZUdEeq-KoPaR9_Cfg _pnZqcpUdEeq-KoPaR9_Cfg _pnZqdJUdEeq-KoPaR9_Cfg _pnaRgZUdEeq-KoPaR9_Cfg _poq1wJUdEeq-KoPaR9_Cfg _poq1wZUdEeq-KoPaR9_Cfg _poq1wpUdEeq-KoPaR9_Cfg _poq1w5UdEeq-KoPaR9_Cfg _poq1xJUdEeq-KoPaR9_Cfg _porc0JUdEeq-KoPaR9_Cfg"/>
    <resources id="_porc0ZUdEeq-KoPaR9_Cfg" name="LinkType" resourceProperties="_pna4kZUdEeq-KoPaR9_Cfg _pnXOMZUdEeq-KoPaR9_Cfg _pna4kJUdEeq-KoPaR9_Cfg _pnX1QJUdEeq-KoPaR9_Cfg _pnYcUJUdEeq-KoPaR9_Cfg _pnZqcpUdEeq-KoPaR9_Cfg _pnZqdJUdEeq-KoPaR9_Cfg _posD4JUdEeq-KoPaR9_Cfg _posD4ZUdEeq-KoPaR9_Cfg"/>
    <configuration xsi:type="oslc4j_ai:MavenSpecificationConfiguration">
      <generalConfiguration filesBasePath="" javaBasePackageName="org.eclipse.lyo.oslc.domains.am"/>
      <projectConfiguration xsi:type="oslc4j_ai:MavenProjectConfiguration" doNotGenerateProjectConfigurationFiles="true" lyoVersion="4.0.0-SNAPSHOT" groupId="org.eclipse.lyo.oslc.domains.am" artifactId="Architecture Management" version="0.0.1-SNAPSHOT"/>
    </configuration>
  </domainSpecifications>
  <domainSpecifications name="Matlab Domain" namespaceURI="http://your.organisation.domain/nsp10#" namespacePrefix="//@domainPrefixes[name='nsp10']"/>
  <domainSpecifications name="Configuration Management" namespaceURI="http://open-services.net/ns/config#" namespacePrefix="//@domainPrefixes[name='oslc_config']">
    <resources id="_pnXOMJUdEeq-KoPaR9_Cfg" name="VersionResource" resourceProperties="_pna4kZUdEeq-KoPaR9_Cfg _pnXOMZUdEeq-KoPaR9_Cfg _pna4kJUdEeq-KoPaR9_Cfg _pnXOMpUdEeq-KoPaR9_Cfg _pnX1QJUdEeq-KoPaR9_Cfg _pnX1QZUdEeq-KoPaR9_Cfg _pnYcUJUdEeq-KoPaR9_Cfg _pnYcUZUdEeq-KoPaR9_Cfg _pnZDYJUdEeq-KoPaR9_Cfg _pnZDYZUdEeq-KoPaR9_Cfg _pnZDYpUdEeq-KoPaR9_Cfg _pnZqcJUdEeq-KoPaR9_Cfg _pnZqcZUdEeq-KoPaR9_Cfg _pnZqcpUdEeq-KoPaR9_Cfg _pnZqc5UdEeq-KoPaR9_Cfg _pnZqdJUdEeq-KoPaR9_Cfg _pnaRgJUdEeq-KoPaR9_Cfg _pnaRgZUdEeq-KoPaR9_Cfg _pnaRgpUdEeq-KoPaR9_Cfg _pnaRg5UdEeq-KoPaR9_Cfg _pnaRhJUdEeq-KoPaR9_Cfg"/>
    <resources id="_pna4kpUdEeq-KoPaR9_Cfg" name="ChangeSet">
      <describes href="vocabulary.xml#//@vocabularies[label='OSLC%20Configuration%20Management']/@classes[name='ChangeSet']"/>
    </resources>
    <resourceProperties id="_pnZDYZUdEeq-KoPaR9_Cfg" name="committed" description="Date and time this version resource was checked in. Absent for mutable (checked out) versions." occurs="zeroOrOne" valueType="DateTime"/>
    <resourceProperties id="_pnZDYpUdEeq-KoPaR9_Cfg" name="committer" description="The entity that checked in this version." occurs="zeroOrMany" readOnly="true" valueType="Resource" representation="either"/>
    <resourceProperties id="_pnZqcJUdEeq-KoPaR9_Cfg" name="component" description="The component to which this version belongs. Configuration Management provider should indicate the owning component for each version resource using either this property, or using the membership relationship from the component LDPC." occurs="zeroOrMany" valueType="String"/>
    <resourceProperties id="_pnZqcZUdEeq-KoPaR9_Cfg" name="versionId" description="A short human-readable identifier for the version of a resource. All versioned resources should have this property; where the property is present, this identifier must be unique amongst all currently existing versions of the same concept resource. The subject of this property should be the concept resource URI." valueType="String"/>
    <configuration xsi:type="oslc4j_ai:MavenSpecificationConfiguration">
      <generalConfiguration filesBasePath="" javaBasePackageName="org.eclipse.lyo.oslc.domains.config"/>
      <projectConfiguration xsi:type="oslc4j_ai:MavenProjectConfiguration" doNotGenerateProjectConfigurationFiles="true" lyoVersion="4.0.0-SNAPSHOT" groupId="org.eclipse.lyo.oslc.domains.config" artifactId="Configuration Management" version="0.0.1-SNAPSHOT"/>
    </configuration>
  </domainSpecifications>
  <domainSpecifications name="Provenance" namespaceURI="http://www.w3.org/ns/prov#" namespacePrefix="//@domainPrefixes[name='prov']">
    <resourceProperties id="_pnaRhJUdEeq-KoPaR9_Cfg" name="wasRevisionOf" description="A resource from which this version was derived. This is likely to reference an earlier version of the same concept resource; use of prov:wasDerivedFrom is recommended to indicate an earlier version of a different concept resource. The subject of each instance of this property must be the concept resource URI; the object is likely to be a version resource URI." occurs="zeroOrMany" valueType="Resource" representation="reference"/>
    <resourceProperties id="_pnaRg5UdEeq-KoPaR9_Cfg" name="wasDerivedFrom" description="A resource from which this version was derived. This is likely to reference a different concept resource; use of prov:wasRevisionOf is recommended to indicate an earlier version of the same concept resource. The subject of each instance of this property must be the concept resource URI; the object can be a version resource URI, or a concept resource URI (possibly for a non-versioned resource)." occurs="zeroOrMany" valueType="Resource" representation="reference"/>
    <configuration xsi:type="oslc4j_ai:MavenSpecificationConfiguration">
      <generalConfiguration filesBasePath="" javaBasePackageName=""/>
      <projectConfiguration xsi:type="oslc4j_ai:MavenProjectConfiguration" doNotGenerateProjectConfigurationFiles="true" lyoVersion="4.0.0-SNAPSHOT" groupId="" artifactId="Provenance" version="0.0.1-SNAPSHOT"/>
    </configuration>
  </domainSpecifications>
  <domainSpecifications name="Automation" namespaceURI="http://open-services.net/ns/auto#" namespacePrefix="//@domainPrefixes[name='oslc_auto']">
    <resources id="_pn-SMJUdEeq-KoPaR9_Cfg" name="AutomationPlan" resourceProperties="_pna4kZUdEeq-KoPaR9_Cfg _pnXOMZUdEeq-KoPaR9_Cfg _pna4kJUdEeq-KoPaR9_Cfg _pnXOMpUdEeq-KoPaR9_Cfg _pnX1QJUdEeq-KoPaR9_Cfg _pnYcUJUdEeq-KoPaR9_Cfg _pnaRgpUdEeq-KoPaR9_Cfg _pnYcUZUdEeq-KoPaR9_Cfg _pnZDYJUdEeq-KoPaR9_Cfg _pnZqcpUdEeq-KoPaR9_Cfg _pnZqdJUdEeq-KoPaR9_Cfg _pn_gUJUdEeq-KoPaR9_Cfg _pn_gUZUdEeq-KoPaR9_Cfg _poAHYJUdEeq-KoPaR9_Cfg"/>
    <resources id="_poAHYZUdEeq-KoPaR9_Cfg" name="AutomationRequest" resourceProperties="_pna4kZUdEeq-KoPaR9_Cfg _pnXOMZUdEeq-KoPaR9_Cfg _pna4kJUdEeq-KoPaR9_Cfg _pnXOMpUdEeq-KoPaR9_Cfg _pnX1QJUdEeq-KoPaR9_Cfg _pnYcUJUdEeq-KoPaR9_Cfg _pnaRgpUdEeq-KoPaR9_Cfg _pnZDYJUdEeq-KoPaR9_Cfg _pnZqcpUdEeq-KoPaR9_Cfg _pnZqdJUdEeq-KoPaR9_Cfg _poBVgJUdEeq-KoPaR9_Cfg _poBVgZUdEeq-KoPaR9_Cfg _poEY0JUdEeq-KoPaR9_Cfg _poEY0ZUdEeq-KoPaR9_Cfg"/>
    <resources id="_poB8kJUdEeq-KoPaR9_Cfg" name="ParameterInstance" resourceProperties="_poB8kZUdEeq-KoPaR9_Cfg _poB8kpUdEeq-KoPaR9_Cfg _pnXOMpUdEeq-KoPaR9_Cfg _pnaRgpUdEeq-KoPaR9_Cfg _pnZqcpUdEeq-KoPaR9_Cfg _pnZqdJUdEeq-KoPaR9_Cfg"/>
    <resources id="_poCjoJUdEeq-KoPaR9_Cfg" name="AutomationResult" resourceProperties="_pna4kZUdEeq-KoPaR9_Cfg _pnXOMZUdEeq-KoPaR9_Cfg _pna4kJUdEeq-KoPaR9_Cfg _pnX1QJUdEeq-KoPaR9_Cfg _pnYcUJUdEeq-KoPaR9_Cfg _pnaRgpUdEeq-KoPaR9_Cfg _pnYcUZUdEeq-KoPaR9_Cfg _pnZDYJUdEeq-KoPaR9_Cfg _pnZqcpUdEeq-KoPaR9_Cfg _pnZqdJUdEeq-KoPaR9_Cfg _poBVgJUdEeq-KoPaR9_Cfg _poBVgZUdEeq-KoPaR9_Cfg _poDxwJUdEeq-KoPaR9_Cfg _poDxwZUdEeq-KoPaR9_Cfg _poEY0JUdEeq-KoPaR9_Cfg _poEY0pUdEeq-KoPaR9_Cfg _poEY05UdEeq-KoPaR9_Cfg _poE_4JUdEeq-KoPaR9_Cfg"/>
    <resourceProperties id="_pn_gUJUdEeq-KoPaR9_Cfg" name="parameterDefinition" description="The definition of a parameter for this Automation Plan. parameterDefinitions are either a local (inline) or referenced resource and use the attributes (the range) of the  oslc:Property resource with one exception. When used in the context of an oslc_auto:parameterDefinition, the cardinality of oslc:propertyDefinition becomes zero-or-one instead of exactly-one. Automation consumers creating Automation Requests MUST use the oslc:occurs attribute of the parameterDefinition, if present, to determine if a given parameter is required when creating the Automation Request. If the oslc:occurs attribute indicates the parameter is required (exactly-one or one-or-more), the service provider must guarantee the named parameter will be present in the Automation Result either as an oslc_auto:inputParmeter when unmodified during execution, or as an oslc_auto:outputParameter when modified during execution." occurs="zeroOrMany" valueType="Resource" representation="either"/>
    <resourceProperties id="_pn_gUZUdEeq-KoPaR9_Cfg" name="usesExecutionEnvironment" description="A resource representing the environment(s) which this Automation Plan can be executed in. The execution environment resource could represent a grouping of environmental details such as operating system, database, browser, compiler, etc. See also the execution environments section." occurs="zeroOrMany" valueType="Resource" representation="reference"/>
    <resourceProperties id="_poAHYJUdEeq-KoPaR9_Cfg" name="futureAction" description="A resource representing actions that will become available on Automation Results that result from execution of this Plan. The resource is likely to be of type oslc:Action, but it can be of any type. Automation defines oslc_auto:TeardownAction as one kind of future action." occurs="zeroOrMany" valueType="Resource" representation="reference"/>
    <resourceProperties id="_poBVgJUdEeq-KoPaR9_Cfg" name="state" description="Used to indicate the state of the automation request based on values defined by the service provider. Most often a read-only property. It is expected that this will be a resource reference to a definition of a valid automation request state on the service provider." occurs="oneOrMany" readOnly="true" valueType="Resource" representation="either"/>
    <resourceProperties id="_poBVgZUdEeq-KoPaR9_Cfg" name="desiredState" description="Used to indicate the desired state of the Automation Request based on values defined by the service provider. It is expected that this will be a resource reference to a definition of a valid automation request state on the service provider." occurs="zeroOrOne" valueType="Resource"/>
    <resourceProperties id="_poEY0JUdEeq-KoPaR9_Cfg" name="inputParameter" description="Parameters provided when Automation Requests are created. These include parameters provided by the creator of the Automation Request (whether by delegated UI or HTTP POST) and MAY include additional parameters added by the service provider during Automation Request creation. See the definition of the oslc_auto:parameterDefinition attribute of the Automation Plan for additional guidance on determining which parameters are required. Creators of Automation Requests MAY provide parameters beyond those defined in the Automation Plan without guarantee the service provider will recognize or honor them. It is expected that this attribute is write-able on Automation Request creation and read-only thereafter." occurs="zeroOrMany" valueType="Resource" range="_poB8kJUdEeq-KoPaR9_Cfg"/>
    <resourceProperties id="_poEY0ZUdEeq-KoPaR9_Cfg" name="executesAutomationPlan" description="Automation Plan run by the Automation Request. It is likely that the target resource will be an oslc_auto:AutomationPlan but that is not necessarily the case." valueType="Resource" range="_pn-SMJUdEeq-KoPaR9_Cfg" representation="reference"/>
    <resourceProperties id="_poDxwJUdEeq-KoPaR9_Cfg" name="verdict" description="Used to indicate the verdict of the automation result based on values defined by the service provider. Most often a read-only property. It is expected that this will be a resource reference to a definition of a valid automation result verdict on the service provider." occurs="oneOrMany" valueType="Resource" representation="either"/>
    <resourceProperties id="_poDxwZUdEeq-KoPaR9_Cfg" name="contribution" description="A result contribution associated with this automation result. It is recommended that the contribution be an inline resource which can be retrieved with the automation result. The recommended attributes beyond the contribution itself are dcterms:title, dcterms:description and dcterms:type to provide a description of the contribution which would be appropriate for display in a simple UI for an automation result." occurs="zeroOrMany" valueType="Resource" representation="either"/>
    <resourceProperties id="_poEY0pUdEeq-KoPaR9_Cfg" name="outputParameter" description="Automation Result output parameters are parameters associated with the automation execution which produced this Result. This includes the final value of all parameters used to initiate the execution and any additional parameters which may have been created during automation execution by the service provider or external agents. The value of a given oslc_auto:outputParameter MAY change as the execution proceeds. Point-in-time accuracy of the values of output parameters is not covered by this specification. Once the Automation Result is in a final state ( oslc_auto:complete or oslc_auto:canceled), the oslc_auto:outputParameter values MUST NOT change." occurs="zeroOrMany" valueType="Resource" range="_poB8kJUdEeq-KoPaR9_Cfg" representation="either"/>
    <resourceProperties id="_poEY05UdEeq-KoPaR9_Cfg" name="producedByAutomationRequest" description="Automation Request which produced the Automation Result. It is likely that the target resource will be an oslc_auto:AutomationRequest but that is not necessarily the case." occurs="zeroOrOne" valueType="Resource" range="_poAHYZUdEeq-KoPaR9_Cfg" representation="reference"/>
    <resourceProperties id="_poE_4JUdEeq-KoPaR9_Cfg" name="reportsOnAutomationPlan" description="Automation Plan which the Automation Result reports on. It is likely that the target resource will be an oslc_auto:AutomationPlan but that is not necessarily the case." valueType="Resource" range="_pn-SMJUdEeq-KoPaR9_Cfg" representation="reference"/>
    <configuration xsi:type="oslc4j_ai:MavenSpecificationConfiguration">
      <generalConfiguration filesBasePath="" javaBasePackageName="org.eclipse.lyo.oslc.domains.auto"/>
      <projectConfiguration xsi:type="oslc4j_ai:MavenProjectConfiguration" doNotGenerateProjectConfigurationFiles="true" lyoVersion="4.0.0-SNAPSHOT" groupId="org.eclipse.lyo.oslc.domains.auto" artifactId="Automation" version="0.0.1-SNAPSHOT"/>
    </configuration>
  </domainSpecifications>
  <domainSpecifications name="Jazz Architecture Management " namespaceURI="http://jazz.net/ns/dm/linktypes#" namespacePrefix="//@domainPrefixes[name='jazz_am']">
    <resourceProperties id="_poq1w5UdEeq-KoPaR9_Cfg" title="derives" name="derives" occurs="zeroOrMany" valueType="Resource"/>
    <resourceProperties id="_poq1xJUdEeq-KoPaR9_Cfg" title="elaborates" name="elaborates" occurs="zeroOrMany" valueType="Resource"/>
    <resourceProperties id="_poq1wJUdEeq-KoPaR9_Cfg" title="external" name="external" occurs="zeroOrMany" valueType="Resource"/>
    <resourceProperties id="_poq1wpUdEeq-KoPaR9_Cfg" title="refine" name="refine" occurs="zeroOrMany" valueType="Resource"/>
    <resourceProperties id="_porc0JUdEeq-KoPaR9_Cfg" title="satisfy" name="satisfy" occurs="zeroOrMany" valueType="Resource"/>
    <resourceProperties id="_poq1wZUdEeq-KoPaR9_Cfg" title="trace" name="trace" occurs="zeroOrMany" valueType="Resource"/>
    <configuration xsi:type="oslc4j_ai:MavenSpecificationConfiguration">
      <generalConfiguration filesBasePath="" javaBasePackageName="org.eclipse.lyo.oslc.domains.jazz_am"/>
      <projectConfiguration xsi:type="oslc4j_ai:MavenProjectConfiguration" doNotGenerateProjectConfigurationFiles="true" lyoVersion="4.0.0-SNAPSHOT" groupId="jazz-architecture-management-" artifactId="jazz-architecture-management-" version="0.0.1-SNAPSHOT"/>
    </configuration>
  </domainSpecifications>
  <domainPrefixes name="dcterms"/>
  <domainPrefixes name="foaf"/>
  <domainPrefixes name="rdf"/>
  <domainPrefixes name="rdfs"/>
  <domainPrefixes name="oslc"/>
  <domainPrefixes name="oslc_cm"/>
  <domainPrefixes name="oslc_rm"/>
  <domainPrefixes name="oslc_qm"/>
  <domainPrefixes name="oslc_am"/>
  <domainPrefixes name="nsp10"/>
  <domainPrefixes name="oslc_config"/>
  <domainPrefixes name="prov"/>
  <domainPrefixes name="oslc_auto"/>
  <domainPrefixes name="jazz_am"/>
  <configuration xsi:type="oslc4j_ai:MavenSpecificationConfiguration">
    <generalConfiguration filesBasePath="." javaBasePackageName="org.eclipse.lyo.oslc.domains"/>
    <projectConfiguration xsi:type="oslc4j_ai:MavenProjectConfiguration" lyoVersion="4.0.0-SNAPSHOT" groupId="org.eclipse.lyo" artifactId="oslc-domains" version="4.0.0-SNAPSHOT"/>
  </configuration>
</oslc4j_ai:Specification>
